skill_caffeinewiz/LICENSE.md
skill_caffeinewiz/README.md
skill_caffeinewiz/__init__.py
skill_caffeinewiz/skill.json
skill_caffeinewiz/version.py
skill_caffeinewiz/data/caffeine_wiz_data.pickle
skill_caffeinewiz/locale/de-de/dialog/drink_caffeine.dialog
skill_caffeinewiz/locale/de-de/regex/drink.rx
skill_caffeinewiz/locale/de-de/vocab/goodbye.voc
skill_caffeinewiz/locale/de-de/vocab/query_caffeine.voc
skill_caffeinewiz/locale/en-us/dialog/drink_caffeine.dialog
skill_caffeinewiz/locale/en-us/dialog/how_about_more.dialog
skill_caffeinewiz/locale/en-us/dialog/more_drinks.dialog
skill_caffeinewiz/locale/en-us/dialog/multiple_drinks.dialog
skill_caffeinewiz/locale/en-us/dialog/no_drink_heard.dialog
skill_caffeinewiz/locale/en-us/dialog/not_found.dialog
skill_caffeinewiz/locale/en-us/dialog/one_moment.dialog
skill_caffeinewiz/locale/en-us/dialog/provided_by_caffeinewiz.dialog
skill_caffeinewiz/locale/en-us/dialog/stay_caffeinated.dialog
skill_caffeinewiz/locale/en-us/dialog/update_complete.dialog
skill_caffeinewiz/locale/en-us/dialog/update_error.dialog
skill_caffeinewiz/locale/en-us/dialog/updating.dialog
skill_caffeinewiz/locale/en-us/dialog/word_liter.dialog
skill_caffeinewiz/locale/en-us/dialog/word_milligrams.dialog
skill_caffeinewiz/locale/en-us/dialog/word_milliliters.dialog
skill_caffeinewiz/locale/en-us/dialog/word_ounces.dialog
skill_caffeinewiz/locale/en-us/regex/drink.rx
skill_caffeinewiz/locale/en-us/vocab/caffeine.voc
skill_caffeinewiz/locale/en-us/vocab/goodbye.voc
skill_caffeinewiz/locale/en-us/vocab/query_caffeine.voc
skill_caffeinewiz/locale/en-us/vocab/update_caffeine.voc
skill_caffeinewiz/neon_skill_caffeinewiz.egg-info/PKG-INFO
skill_caffeinewiz/neon_skill_caffeinewiz.egg-info/SOURCES.txt
skill_caffeinewiz/neon_skill_caffeinewiz.egg-info/dependency_links.txt
skill_caffeinewiz/neon_skill_caffeinewiz.egg-info/entry_points.txt
skill_caffeinewiz/neon_skill_caffeinewiz.egg-info/requires.txt
skill_caffeinewiz/neon_skill_caffeinewiz.egg-info/top_level.txt
skill_caffeinewiz/test/test_skill.py
neon_skill_caffeinewiz-2.0.0.dist-info/LICENSE.md
neon_skill_caffeinewiz-2.0.0.dist-info/METADATA
neon_skill_caffeinewiz-2.0.0.dist-info/WHEEL
neon_skill_caffeinewiz-2.0.0.dist-info/entry_points.txt
neon_skill_caffeinewiz-2.0.0.dist-info/top_level.txt
neon_skill_caffeinewiz-2.0.0.dist-info/RECORD
